[
  {
    "arch": "20-10-1",
    "seed": 42,
    "bits": 18,
    "query_count": 1384264,
    "wallclock_s": 7.141549110412598,
    "n_sweeps": 40,
    "n_probes": 400,
    "grad_target_levels": 64,
    "grad_init_radius": 0.001,
    "grad_max_radius": 0.05,
    "jump_threshold": 0.05,
    "sim_threshold": 0.85,
    "use_mitm": true,
    "extraction_success": true,
    "max_logit_loss": 1.0516395558654712,
    "mean_logit_loss": 0.17453376987502484,
    "rel_loss": 0.05781971667506804,
    "case": "baseline"
  },
  {
    "arch": "20-10-1",
    "seed": 42,
    "bits": 18,
    "query_count": 691252,
    "wallclock_s": 3.3171539306640625,
    "n_sweeps": 20,
    "n_probes": 400,
    "grad_target_levels": 64,
    "grad_init_radius": 0.001,
    "grad_max_radius": 0.05,
    "jump_threshold": 0.05,
    "sim_threshold": 0.85,
    "use_mitm": true,
    "extraction_success": true,
    "max_logit_loss": 5.563158319157148,
    "mean_logit_loss": 0.7460937982630529,
    "rel_loss": 0.2471666775976064,
    "case": "n_sweeps_low"
  },
  {
    "arch": "20-10-1",
    "seed": 42,
    "bits": 18,
    "query_count": 2796763,
    "wallclock_s": 13.287160158157349,
    "n_sweeps": 80,
    "n_probes": 400,
    "grad_target_levels": 64,
    "grad_init_radius": 0.001,
    "grad_max_radius": 0.05,
    "jump_threshold": 0.05,
    "sim_threshold": 0.85,
    "use_mitm": true,
    "extraction_success": true,
    "max_logit_loss": 2.1731166380495015,
    "mean_logit_loss": 0.3015645190741857,
    "rel_loss": 0.09990258655736314,
    "case": "n_sweeps_high"
  },
  {
    "arch": "20-10-1",
    "seed": 42,
    "bits": 18,
    "query_count": 693523,
    "wallclock_s": 3.2869367599487305,
    "n_sweeps": 40,
    "n_probes": 200,
    "grad_target_levels": 64,
    "grad_init_radius": 0.001,
    "grad_max_radius": 0.05,
    "jump_threshold": 0.05,
    "sim_threshold": 0.85,
    "use_mitm": true,
    "extraction_success": true,
    "max_logit_loss": 0.5708036437329476,
    "mean_logit_loss": 0.0739144418946759,
    "rel_loss": 0.024486448047309917,
    "case": "n_probes_low"
  },
  {
    "arch": "20-10-1",
    "seed": 42,
    "bits": 18,
    "query_count": 2083141,
    "wallclock_s": 9.742664098739624,
    "n_sweeps": 40,
    "n_probes": 600,
    "grad_target_levels": 64,
    "grad_init_radius": 0.001,
    "grad_max_radius": 0.05,
    "jump_threshold": 0.05,
    "sim_threshold": 0.85,
    "use_mitm": true,
    "extraction_success": true,
    "max_logit_loss": 5.224736008705571,
    "mean_logit_loss": 0.9070581492318821,
    "rel_loss": 0.3004911040078544,
    "case": "n_probes_high"
  },
  {
    "arch": "20-10-1",
    "seed": 42,
    "bits": 18,
    "query_count": 1384264,
    "wallclock_s": 6.829567193984985,
    "n_sweeps": 40,
    "n_probes": 400,
    "grad_target_levels": 64,
    "grad_init_radius": 0.001,
    "grad_max_radius": 0.05,
    "jump_threshold": 0.03,
    "sim_threshold": 0.85,
    "use_mitm": true,
    "extraction_success": true,
    "max_logit_loss": 5.026309979826629,
    "mean_logit_loss": 0.756160201965744,
    "rel_loss": 0.25050148558601587,
    "case": "jump_threshold_low"
  },
  {
    "arch": "20-10-1",
    "seed": 42,
    "bits": 18,
    "query_count": 1384264,
    "wallclock_s": 7.13053297996521,
    "n_sweeps": 40,
    "n_probes": 400,
    "grad_target_levels": 64,
    "grad_init_radius": 0.001,
    "grad_max_radius": 0.05,
    "jump_threshold": 0.08,
    "sim_threshold": 0.85,
    "use_mitm": true,
    "extraction_success": true,
    "max_logit_loss": 0.9854884789012623,
    "mean_logit_loss": 0.15231431071663265,
    "rel_loss": 0.05045883268034651,
    "case": "jump_threshold_high"
  },
  {
    "arch": "20-10-1",
    "seed": 42,
    "bits": 18,
    "query_count": 1384264,
    "wallclock_s": 8.756095170974731,
    "n_sweeps": 40,
    "n_probes": 400,
    "grad_target_levels": 64,
    "grad_init_radius": 0.001,
    "grad_max_radius": 0.05,
    "jump_threshold": 0.05,
    "sim_threshold": 0.8,
    "use_mitm": true,
    "extraction_success": true,
    "max_logit_loss": 3.9071700725415885,
    "mean_logit_loss": 0.6088712850345842,
    "rel_loss": 0.20170747023623384,
    "case": "sim_threshold_low"
  },
  {
    "arch": "20-10-1",
    "seed": 42,
    "bits": 18,
    "query_count": 1384264,
    "wallclock_s": 9.919096946716309,
    "n_sweeps": 40,
    "n_probes": 400,
    "grad_target_levels": 64,
    "grad_init_radius": 0.001,
    "grad_max_radius": 0.05,
    "jump_threshold": 0.05,
    "sim_threshold": 0.9,
    "use_mitm": true,
    "extraction_success": true,
    "max_logit_loss": 4.219708528651493,
    "mean_logit_loss": 0.578725047631724,
    "rel_loss": 0.19172059545148115,
    "case": "sim_threshold_high"
  },
  {
    "arch": "20-10-1",
    "seed": 42,
    "bits": 16,
    "query_count": 3427792,
    "wallclock_s": 23.29851222038269,
    "n_sweeps": 40,
    "n_probes": 600,
    "grad_target_levels": 64,
    "grad_init_radius": 0.001,
    "grad_max_radius": 0.05,
    "jump_threshold": 0.05,
    "sim_threshold": 0.85,
    "use_mitm": true,
    "extraction_success": true,
    "max_logit_loss": 14.975659396654535,
    "mean_logit_loss": 1.9781941546404196,
    "rel_loss": 0.6553380794529665,
    "case": "baseline"
  },
  {
    "arch": "20-10-1",
    "seed": 42,
    "bits": 16,
    "query_count": 1734829,
    "wallclock_s": 11.893304824829102,
    "n_sweeps": 20,
    "n_probes": 600,
    "grad_target_levels": 64,
    "grad_init_radius": 0.001,
    "grad_max_radius": 0.05,
    "jump_threshold": 0.05,
    "sim_threshold": 0.85,
    "use_mitm": true,
    "extraction_success": true,
    "max_logit_loss": 15.958711853099697,
    "mean_logit_loss": 2.0196320787868,
    "rel_loss": 0.6690656751810727,
    "case": "n_sweeps_low"
  },
  {
    "arch": "20-10-1",
    "seed": 42,
    "bits": 16,
    "query_count": 6861670,
    "wallclock_s": 49.12061405181885,
    "n_sweeps": 80,
    "n_probes": 600,
    "grad_target_levels": 64,
    "grad_init_radius": 0.001,
    "grad_max_radius": 0.05,
    "jump_threshold": 0.05,
    "sim_threshold": 0.85,
    "use_mitm": true,
    "extraction_success": true,
    "max_logit_loss": 13.683738940185876,
    "mean_logit_loss": 1.949408599133628,
    "rel_loss": 0.6458019726873309,
    "case": "n_sweeps_high"
  },
  {
    "arch": "20-10-1",
    "seed": 42,
    "bits": 16,
    "query_count": 2284333,
    "wallclock_s": 13.753166913986206,
    "n_sweeps": 40,
    "n_probes": 400,
    "grad_target_levels": 64,
    "grad_init_radius": 0.001,
    "grad_max_radius": 0.05,
    "jump_threshold": 0.05,
    "sim_threshold": 0.85,
    "use_mitm": true,
    "extraction_success": true,
    "max_logit_loss": 13.701204820544369,
    "mean_logit_loss": 1.8256597269729165,
    "rel_loss": 0.6048063262155048,
    "case": "n_probes_low"
  },
  {
    "arch": "20-10-1",
    "seed": 42,
    "bits": 16,
    "query_count": 4569730,
    "wallclock_s": 28.506829977035522,
    "n_sweeps": 40,
    "n_probes": 800,
    "grad_target_levels": 64,
    "grad_init_radius": 0.001,
    "grad_max_radius": 0.05,
    "jump_threshold": 0.05,
    "sim_threshold": 0.85,
    "use_mitm": true,
    "extraction_success": true,
    "max_logit_loss": 16.14785586569558,
    "mean_logit_loss": 2.120650242805616,
    "rel_loss": 0.702531070598738,
    "case": "n_probes_high"
  },
  {
    "arch": "20-10-1",
    "seed": 42,
    "bits": 16,
    "query_count": 3427792,
    "wallclock_s": 20.652889013290405,
    "n_sweeps": 40,
    "n_probes": 600,
    "grad_target_levels": 64,
    "grad_init_radius": 0.001,
    "grad_max_radius": 0.05,
    "jump_threshold": 0.03,
    "sim_threshold": 0.85,
    "use_mitm": true,
    "extraction_success": true,
    "max_logit_loss": 14.832201156734374,
    "mean_logit_loss": 2.047131359868648,
    "rel_loss": 0.6781756637068408,
    "case": "jump_threshold_low"
  },
  {
    "arch": "20-10-1",
    "seed": 42,
    "bits": 16,
    "query_count": 3427792,
    "wallclock_s": 20.740148782730103,
    "n_sweeps": 40,
    "n_probes": 600,
    "grad_target_levels": 64,
    "grad_init_radius": 0.001,
    "grad_max_radius": 0.05,
    "jump_threshold": 0.08,
    "sim_threshold": 0.85,
    "use_mitm": true,
    "extraction_success": true,
    "max_logit_loss": 16.51043908135671,
    "mean_logit_loss": 2.0456786871690795,
    "rel_loss": 0.6776944208850603,
    "case": "jump_threshold_high"
  },
  {
    "arch": "20-10-1",
    "seed": 42,
    "bits": 16,
    "query_count": 3427792,
    "wallclock_s": 21.313733100891113,
    "n_sweeps": 40,
    "n_probes": 600,
    "grad_target_levels": 64,
    "grad_init_radius": 0.001,
    "grad_max_radius": 0.05,
    "jump_threshold": 0.05,
    "sim_threshold": 0.8,
    "use_mitm": true,
    "extraction_success": true,
    "max_logit_loss": 15.191632622305274,
    "mean_logit_loss": 2.002789236907304,
    "rel_loss": 0.6634859621766911,
    "case": "sim_threshold_low"
  },
  {
    "arch": "20-10-1",
    "seed": 42,
    "bits": 16,
    "query_count": 3427792,
    "wallclock_s": 20.34624218940735,
    "n_sweeps": 40,
    "n_probes": 600,
    "grad_target_levels": 64,
    "grad_init_radius": 0.001,
    "grad_max_radius": 0.05,
    "jump_threshold": 0.05,
    "sim_threshold": 0.9,
    "use_mitm": true,
    "extraction_success": true,
    "max_logit_loss": 14.141936947742192,
    "mean_logit_loss": 1.9817814093786674,
    "rel_loss": 0.6565264686842042,
    "case": "sim_threshold_high"
  }
]